[
  {
    "full_name": "radix-ui/primitives",
    "stargazers_count": 2101,
    "open_issues_count": 75,
    "forks_count": 69
  },
  {
    "full_name": "modulz/stitches",
    "stargazers_count": 4132,
    "open_issues_count": 49,
    "forks_count": 108
  },
  {
    "full_name": "the-pudding/website",
    "stargazers_count": 22,
    "open_issues_count": 16,
    "forks_count": 0
  },
  {
    "full_name": "donnemartin/system-design-primer",
    "stargazers_count": 148965,
    "open_issues_count": 261,
    "forks_count": 27515
  },
  {
    "full_name": "android/compose-samples",
    "stargazers_count": 9572,
    "open_issues_count": 61,
    "forks_count": 1919
  },
  {
    "full_name": "afollestad/material-dialogs",
    "stargazers_count": 19067,
    "open_issues_count": 109,
    "forks_count": 3121
  },
  {
    "full_name": "skrapeit/skrape.it",
    "stargazers_count": 416,
    "open_issues_count": 15,
    "forks_count": 34
  },
  {
    "full_name": "ponnamkarthik/RichLinkPreview",
    "stargazers_count": 188,
    "open_issues_count": 22,
    "forks_count": 44
  },
  {
    "full_name": "savepopulation/beaver",
    "stargazers_count": 63,
    "open_issues_count": 0,
    "forks_count": 5
  },
  {
    "full_name": "chimbori/crux",
    "stargazers_count": 154,
    "open_issues_count": 10,
    "forks_count": 32
  },
  {
    "full_name": "cdimascio/essence",
    "stargazers_count": 76,
    "open_issues_count": 4,
    "forks_count": 10
  },
  {
    "full_name": "velocityzen/meta-extractor",
    "stargazers_count": 35,
    "open_issues_count": 3,
    "forks_count": 5
  },
  {
    "full_name": "dennybritz/url-metadata-extractor",
    "stargazers_count": 23,
    "open_issues_count": 0,
    "forks_count": 6
  },
  {
    "full_name": "Solido/awesome-flutter",
    "stargazers_count": 38065,
    "open_issues_count": 40,
    "forks_count": 5536
  },
  {
    "full_name": "singerdmx/flutter-quill",
    "stargazers_count": 631,
    "open_issues_count": 20,
    "forks_count": 177
  },
  {
    "full_name": "BertrandBev/code_field",
    "stargazers_count": 70,
    "open_issues_count": 9,
    "forks_count": 14
  },
  {
    "full_name": "TakuSemba/MultiSnapRecyclerView",
    "stargazers_count": 2345,
    "open_issues_count": 3,
    "forks_count": 300
  },
  {
    "full_name": "shikijs/shiki",
    "stargazers_count": 2743,
    "open_issues_count": 35,
    "forks_count": 100
  },
  {
    "full_name": "LiquidPlayer/LiquidCore",
    "stargazers_count": 840,
    "open_issues_count": 50,
    "forks_count": 103
  },
  {
    "full_name": "evgenyneu/js-evaluator-for-android",
    "stargazers_count": 438,
    "open_issues_count": 19,
    "forks_count": 79
  },
  {
    "full_name": "ernestoyaquello/DragDropSwipeRecyclerview",
    "stargazers_count": 610,
    "open_issues_count": 4,
    "forks_count": 74
  },
  {
    "full_name": "maxkeppeler/sheets",
    "stargazers_count": 664,
    "open_issues_count": 8,
    "forks_count": 50
  },
  {
    "full_name": "afollestad/recyclical",
    "stargazers_count": 692,
    "open_issues_count": 12,
    "forks_count": 58
  },
  {
    "full_name": "nikhilpanju/FabFilter",
    "stargazers_count": 1459,
    "open_issues_count": 5,
    "forks_count": 207
  },
  {
    "full_name": "MindorksOpenSource/android-developer-roadmap",
    "stargazers_count": 2134,
    "open_issues_count": 11,
    "forks_count": 422
  },
  {
    "full_name": "ibrahimsn98/SmoothBottomBar",
    "stargazers_count": 1479,
    "open_issues_count": 31,
    "forks_count": 189
  },
  {
    "full_name": "android/databinding-samples",
    "stargazers_count": 1471,
    "open_issues_count": 25,
    "forks_count": 408
  },
  {
    "full_name": "saket/cascade",
    "stargazers_count": 1480,
    "open_issues_count": 5,
    "forks_count": 40
  },
  {
    "full_name": "skydoves/TransformationLayout",
    "stargazers_count": 1644,
    "open_issues_count": 5,
    "forks_count": 142
  },
  {
    "full_name": "afollestad/drag-select-recyclerview",
    "stargazers_count": 1810,
    "open_issues_count": 2,
    "forks_count": 215
  }
]